django_rundbg/__init__.py
django_rundbg/werkzeug_patch.py
django_rundbg/management/commands/__init__.py
django_rundbg/management/commands/rundbg.py
django_rundbg-0.1.3.dist-info/DESCRIPTION.rst
django_rundbg-0.1.3.dist-info/METADATA
django_rundbg-0.1.3.dist-info/RECORD
django_rundbg-0.1.3.dist-info/WHEEL
django_rundbg-0.1.3.dist-info/metadata.json
django_rundbg-0.1.3.dist-info/top_level.txt
django_rundbg-0.1.3.dist-info/zip-safe
