Metadata-Version: 2.0
Name: django-rundbg
Version: 0.1.3
Summary: Provides a lightweight development runserver on Werkzeug with debugging
Home-page: https://github.com/octobot-dev/django-rundbg
Author: Juan Saavedra
Author-email: jsaavedra@octobot.io
License: Apache License
Download-URL: https://github.com/octobot-dev/django-rundbg/archive/0.1.3.tar.gz
Keywords: django,debug,django-rest-framework,api
Platform: UNKNOWN
Classifier: Programming Language :: Python
Classifier: Programming Language :: Python :: 2.7
Classifier: Programming Language :: Python :: 3.4
Classifier: Programming Language :: Python :: 3.5
Classifier: Programming Language :: Python :: 3.6
Classifier: Framework :: Django
Classifier: Framework :: Django :: 1.11
Classifier: Framework :: Django :: 1.10
Classifier: Framework :: Django :: 1.9
Classifier: Framework :: Django :: 1.8
Classifier: Framework :: Django :: 1.7
Classifier: Intended Audience :: Developers
Classifier: License :: OSI Approved :: Apache Software License
Classifier: Operating System :: OS Independent
Classifier: Development Status :: 4 - Beta
Classifier: Environment :: Web Environment
Classifier: Intended Audience :: Information Technology
Classifier: Topic :: Internet :: WWW/HTTP :: WSGI :: Application
Requires-Dist: Django (>=1.7)
Requires-Dist: Werkzeug (>=0.11)
